ofspectrum/__init__.py
ofspectrum/client.py
ofspectrum/exceptions.py
ofspectrum/py.typed
ofspectrum/models/__init__.py
ofspectrum/models/audio.py
ofspectrum/models/notebook.py
ofspectrum/models/quota.py
ofspectrum/models/token.py
ofspectrum/resources/__init__.py
ofspectrum/resources/audio.py
ofspectrum/resources/base.py
ofspectrum/resources/notebooks.py
ofspectrum/resources/quotas.py
ofspectrum/resources/tokens.py
ofspectrum/resources/webhooks.py
ofspectrum/utils/__init__.py
ofspectrum/utils/retry.py
ofspectrum-1.1.3.dist-info/METADATA
ofspectrum-1.1.3.dist-info/WHEEL
ofspectrum-1.1.3.dist-info/top_level.txt
ofspectrum-1.1.3.dist-info/RECORD
