Metadata-Version: 2.4
Name: ofspectrum
Version: 1.1.3
Summary: OfSpectrum Audio Watermarking SDK
Author-email: OfSpectrum <dev@ofspectrum.com>
License: MIT
Project-URL: Homepage, https://ofspectrum.com
Project-URL: Documentation, https://api.ofspectrum.com/docs
Project-URL: Repository, https://github.com/ofspectrum/python-sdk
Keywords: audio,watermark,api,sdk,ofspectrum
Classifier: Development Status :: 4 - Beta
Classifier: Intended Audience :: Developers
Classifier: License :: OSI Approved :: MIT License
Classifier: Operating System :: OS Independent
Classifier: Programming Language :: Python :: 3
Classifier: Programming Language :: Python :: 3.8
Classifier: Programming Language :: Python :: 3.9
Classifier: Programming Language :: Python :: 3.10
Classifier: Programming Language :: Python :: 3.11
Classifier: Programming Language :: Python :: 3.12
Classifier: Topic :: Multimedia :: Sound/Audio
Classifier: Typing :: Typed
Requires-Python: >=3.8
Requires-Dist: httpx>=0.24.0
Provides-Extra: dev
Requires-Dist: pytest>=7.0.0; extra == "dev"
Requires-Dist: pytest-asyncio>=0.21.0; extra == "dev"
Requires-Dist: ruff>=0.1.0; extra == "dev"
